<?xml version="1.0" encoding="UTF-8"?>
<?xml-stylesheet href="CoreNLP-to-HTML.xsl" type="text/xsl"?>
<root>
  <document>
    <sentences>
      <sentence id="1">
        <tokens>
          <token id="1">
            <word>China</word>
            <lemma>China</lemma>
            <CharacterOffsetBegin>0</CharacterOffsetBegin>
            <CharacterOffsetEnd>5</CharacterOffsetEnd>
            <POS>NNP</POS>
            <NER>LOCATION</NER>
          </token>
          <token id="2">
            <word>'s</word>
            <lemma>'s</lemma>
            <CharacterOffsetBegin>5</CharacterOffsetBegin>
            <CharacterOffsetEnd>7</CharacterOffsetEnd>
            <POS>POS</POS>
            <NER>O</NER>
          </token>
          <token id="3">
            <word>central</word>
            <lemma>central</lemma>
            <CharacterOffsetBegin>8</CharacterOffsetBegin>
            <CharacterOffsetEnd>15</CharacterOffsetEnd>
            <POS>JJ</POS>
            <NER>O</NER>
          </token>
          <token id="4">
            <word>bank</word>
            <lemma>bank</lemma>
            <CharacterOffsetBegin>16</CharacterOffsetBegin>
            <CharacterOffsetEnd>20</CharacterOffsetEnd>
            <POS>NN</POS>
            <NER>O</NER>
          </token>
          <token id="5">
            <word>said</word>
            <lemma>say</lemma>
            <CharacterOffsetBegin>21</CharacterOffsetBegin>
            <CharacterOffsetEnd>25</CharacterOffsetEnd>
            <POS>VBD</POS>
            <NER>O</NER>
          </token>
          <token id="6">
            <word>late</word>
            <lemma>late</lemma>
            <CharacterOffsetBegin>26</CharacterOffsetBegin>
            <CharacterOffsetEnd>30</CharacterOffsetEnd>
            <POS>JJ</POS>
            <NER>DATE</NER>
            <NormalizedNER>XXXX-WXX-3</NormalizedNER>
            <Timex tid="t1" type="DATE">XXXX-WXX-3</Timex>
          </token>
          <token id="7">
            <word>Wednesday</word>
            <lemma>Wednesday</lemma>
            <CharacterOffsetBegin>31</CharacterOffsetBegin>
            <CharacterOffsetEnd>40</CharacterOffsetEnd>
            <POS>NNP</POS>
            <NER>DATE</NER>
            <NormalizedNER>XXXX-WXX-3</NormalizedNER>
            <Timex tid="t1" type="DATE">XXXX-WXX-3</Timex>
          </token>
          <token id="8">
            <word>that</word>
            <lemma>that</lemma>
            <CharacterOffsetBegin>41</CharacterOffsetBegin>
            <CharacterOffsetEnd>45</CharacterOffsetEnd>
            <POS>IN</POS>
            <NER>O</NER>
          </token>
          <token id="9">
            <word>it</word>
            <lemma>it</lemma>
            <CharacterOffsetBegin>46</CharacterOffsetBegin>
            <CharacterOffsetEnd>48</CharacterOffsetEnd>
            <POS>PRP</POS>
            <NER>O</NER>
          </token>
          <token id="10">
            <word>was</word>
            <lemma>be</lemma>
            <CharacterOffsetBegin>49</CharacterOffsetBegin>
            <CharacterOffsetEnd>52</CharacterOffsetEnd>
            <POS>VBD</POS>
            <NER>O</NER>
          </token>
          <token id="11">
            <word>raising</word>
            <lemma>raise</lemma>
            <CharacterOffsetBegin>53</CharacterOffsetBegin>
            <CharacterOffsetEnd>60</CharacterOffsetEnd>
            <POS>VBG</POS>
            <NER>O</NER>
          </token>
          <token id="12">
            <word>the</word>
            <lemma>the</lemma>
            <CharacterOffsetBegin>61</CharacterOffsetBegin>
            <CharacterOffsetEnd>64</CharacterOffsetEnd>
            <POS>DT</POS>
            <NER>O</NER>
          </token>
          <token id="13">
            <word>interest</word>
            <lemma>interest</lemma>
            <CharacterOffsetBegin>65</CharacterOffsetBegin>
            <CharacterOffsetEnd>73</CharacterOffsetEnd>
            <POS>NN</POS>
            <NER>O</NER>
          </token>
          <token id="14">
            <word>rate</word>
            <lemma>rate</lemma>
            <CharacterOffsetBegin>74</CharacterOffsetBegin>
            <CharacterOffsetEnd>78</CharacterOffsetEnd>
            <POS>NN</POS>
            <NER>O</NER>
          </token>
          <token id="15">
            <word>on</word>
            <lemma>on</lemma>
            <CharacterOffsetBegin>79</CharacterOffsetBegin>
            <CharacterOffsetEnd>81</CharacterOffsetEnd>
            <POS>IN</POS>
            <NER>O</NER>
          </token>
          <token id="16">
            <word>mortgages</word>
            <lemma>mortgage</lemma>
            <CharacterOffsetBegin>82</CharacterOffsetBegin>
            <CharacterOffsetEnd>91</CharacterOffsetEnd>
            <POS>NNS</POS>
            <NER>O</NER>
          </token>
          <token id="17">
            <word>,</word>
            <lemma>,</lemma>
            <CharacterOffsetBegin>91</CharacterOffsetBegin>
            <CharacterOffsetEnd>92</CharacterOffsetEnd>
            <POS>,</POS>
            <NER>O</NER>
          </token>
          <token id="18">
            <word>after</word>
            <lemma>after</lemma>
            <CharacterOffsetBegin>93</CharacterOffsetBegin>
            <CharacterOffsetEnd>98</CharacterOffsetEnd>
            <POS>IN</POS>
            <NER>O</NER>
          </token>
          <token id="19">
            <word>more</word>
            <lemma>more</lemma>
            <CharacterOffsetBegin>99</CharacterOffsetBegin>
            <CharacterOffsetEnd>103</CharacterOffsetEnd>
            <POS>JJR</POS>
            <NER>O</NER>
          </token>
          <token id="20">
            <word>signs</word>
            <lemma>sign</lemma>
            <CharacterOffsetBegin>104</CharacterOffsetBegin>
            <CharacterOffsetEnd>109</CharacterOffsetEnd>
            <POS>NNS</POS>
            <NER>O</NER>
          </token>
          <token id="21">
            <word>emerged</word>
            <lemma>emerge</lemma>
            <CharacterOffsetBegin>110</CharacterOffsetBegin>
            <CharacterOffsetEnd>117</CharacterOffsetEnd>
            <POS>VBD</POS>
            <NER>O</NER>
          </token>
          <token id="22">
            <word>that</word>
            <lemma>that</lemma>
            <CharacterOffsetBegin>118</CharacterOffsetBegin>
            <CharacterOffsetEnd>122</CharacterOffsetEnd>
            <POS>IN</POS>
            <NER>O</NER>
          </token>
          <token id="23">
            <word>the</word>
            <lemma>the</lemma>
            <CharacterOffsetBegin>123</CharacterOffsetBegin>
            <CharacterOffsetEnd>126</CharacterOffsetEnd>
            <POS>DT</POS>
            <NER>O</NER>
          </token>
          <token id="24">
            <word>country</word>
            <lemma>country</lemma>
            <CharacterOffsetBegin>127</CharacterOffsetBegin>
            <CharacterOffsetEnd>134</CharacterOffsetEnd>
            <POS>NN</POS>
            <NER>O</NER>
          </token>
          <token id="25">
            <word>'s</word>
            <lemma>'s</lemma>
            <CharacterOffsetBegin>134</CharacterOffsetBegin>
            <CharacterOffsetEnd>136</CharacterOffsetEnd>
            <POS>POS</POS>
            <NER>O</NER>
          </token>
          <token id="26">
            <word>economy</word>
            <lemma>economy</lemma>
            <CharacterOffsetBegin>137</CharacterOffsetBegin>
            <CharacterOffsetEnd>144</CharacterOffsetEnd>
            <POS>NN</POS>
            <NER>O</NER>
          </token>
          <token id="27">
            <word>might</word>
            <lemma>might</lemma>
            <CharacterOffsetBegin>145</CharacterOffsetBegin>
            <CharacterOffsetEnd>150</CharacterOffsetEnd>
            <POS>MD</POS>
            <NER>O</NER>
          </token>
          <token id="28">
            <word>be</word>
            <lemma>be</lemma>
            <CharacterOffsetBegin>151</CharacterOffsetBegin>
            <CharacterOffsetEnd>153</CharacterOffsetEnd>
            <POS>VB</POS>
            <NER>O</NER>
          </token>
          <token id="29">
            <word>growing</word>
            <lemma>grow</lemma>
            <CharacterOffsetBegin>154</CharacterOffsetBegin>
            <CharacterOffsetEnd>161</CharacterOffsetEnd>
            <POS>VBG</POS>
            <NER>O</NER>
          </token>
          <token id="30">
            <word>at</word>
            <lemma>at</lemma>
            <CharacterOffsetBegin>162</CharacterOffsetBegin>
            <CharacterOffsetEnd>164</CharacterOffsetEnd>
            <POS>IN</POS>
            <NER>O</NER>
          </token>
          <token id="31">
            <word>an</word>
            <lemma>a</lemma>
            <CharacterOffsetBegin>165</CharacterOffsetBegin>
            <CharacterOffsetEnd>167</CharacterOffsetEnd>
            <POS>DT</POS>
            <NER>O</NER>
          </token>
          <token id="32">
            <word>unsustainable</word>
            <lemma>unsustainable</lemma>
            <CharacterOffsetBegin>168</CharacterOffsetBegin>
            <CharacterOffsetEnd>181</CharacterOffsetEnd>
            <POS>JJ</POS>
            <NER>O</NER>
          </token>
          <token id="33">
            <word>pace</word>
            <lemma>pace</lemma>
            <CharacterOffsetBegin>182</CharacterOffsetBegin>
            <CharacterOffsetEnd>186</CharacterOffsetEnd>
            <POS>NN</POS>
            <NER>O</NER>
          </token>
          <token id="34">
            <word>as</word>
            <lemma>as</lemma>
            <CharacterOffsetBegin>187</CharacterOffsetBegin>
            <CharacterOffsetEnd>189</CharacterOffsetEnd>
            <POS>IN</POS>
            <NER>O</NER>
          </token>
          <token id="35">
            <word>property</word>
            <lemma>property</lemma>
            <CharacterOffsetBegin>190</CharacterOffsetBegin>
            <CharacterOffsetEnd>198</CharacterOffsetEnd>
            <POS>NN</POS>
            <NER>O</NER>
          </token>
          <token id="36">
            <word>prices</word>
            <lemma>price</lemma>
            <CharacterOffsetBegin>199</CharacterOffsetBegin>
            <CharacterOffsetEnd>205</CharacterOffsetEnd>
            <POS>NNS</POS>
            <NER>O</NER>
          </token>
          <token id="37">
            <word>soar</word>
            <lemma>soar</lemma>
            <CharacterOffsetBegin>206</CharacterOffsetBegin>
            <CharacterOffsetEnd>210</CharacterOffsetEnd>
            <POS>VB</POS>
            <NER>O</NER>
          </token>
          <token id="38">
            <word>.</word>
            <lemma>.</lemma>
            <CharacterOffsetBegin>210</CharacterOffsetBegin>
            <CharacterOffsetEnd>211</CharacterOffsetEnd>
            <POS>.</POS>
            <NER>O</NER>
          </token>
        </tokens>
        <parse>(ROOT (S (NP (NP (NNP China) (POS 's)) (JJ central) (NN bank)) (VP (VBD said) (NP-TMP (JJ late) (NNP Wednesday)) (SBAR (IN that) (S (NP (PRP it)) (VP (VBD was) (VP (VBG raising) (NP (DT the) (NN interest) (NN rate)) (PP (IN on) (NP (NNS mortgages))) (, ,) (SBAR (IN after) (S (NP (JJR more) (NNS signs)) (VP (VBD emerged) (SBAR (IN that) (S (NP (NP (DT the) (NN country) (POS 's)) (NN economy)) (VP (MD might) (VP (VB be) (VP (VBG growing) (PP (IN at) (NP (DT an) (JJ unsustainable) (NN pace))) (SBAR (IN as) (S (NP (NN property) (NNS prices)) (VP (VB soar))))))))))))))))) (. .))) </parse>
        <basic-dependencies>
          <dep type="poss">
            <governor idx="4">bank</governor>
            <dependent idx="1">China</dependent>
          </dep>
          <dep type="possessive">
            <governor idx="1">China</governor>
            <dependent idx="2">'s</dependent>
          </dep>
          <dep type="amod">
            <governor idx="4">bank</governor>
            <dependent idx="3">central</dependent>
          </dep>
          <dep type="nsubj">
            <governor idx="5">said</governor>
            <dependent idx="4">bank</dependent>
          </dep>
          <dep type="amod">
            <governor idx="7">Wednesday</governor>
            <dependent idx="6">late</dependent>
          </dep>
          <dep type="tmod">
            <governor idx="5">said</governor>
            <dependent idx="7">Wednesday</dependent>
          </dep>
          <dep type="complm">
            <governor idx="11">raising</governor>
            <dependent idx="8">that</dependent>
          </dep>
          <dep type="nsubj">
            <governor idx="11">raising</governor>
            <dependent idx="9">it</dependent>
          </dep>
          <dep type="aux">
            <governor idx="11">raising</governor>
            <dependent idx="10">was</dependent>
          </dep>
          <dep type="ccomp">
            <governor idx="5">said</governor>
            <dependent idx="11">raising</dependent>
          </dep>
          <dep type="det">
            <governor idx="14">rate</governor>
            <dependent idx="12">the</dependent>
          </dep>
          <dep type="nn">
            <governor idx="14">rate</governor>
            <dependent idx="13">interest</dependent>
          </dep>
          <dep type="dobj">
            <governor idx="11">raising</governor>
            <dependent idx="14">rate</dependent>
          </dep>
          <dep type="prep">
            <governor idx="11">raising</governor>
            <dependent idx="15">on</dependent>
          </dep>
          <dep type="pobj">
            <governor idx="15">on</governor>
            <dependent idx="16">mortgages</dependent>
          </dep>
          <dep type="mark">
            <governor idx="21">emerged</governor>
            <dependent idx="18">after</dependent>
          </dep>
          <dep type="amod">
            <governor idx="20">signs</governor>
            <dependent idx="19">more</dependent>
          </dep>
          <dep type="nsubj">
            <governor idx="21">emerged</governor>
            <dependent idx="20">signs</dependent>
          </dep>
          <dep type="advcl">
            <governor idx="11">raising</governor>
            <dependent idx="21">emerged</dependent>
          </dep>
          <dep type="complm">
            <governor idx="29">growing</governor>
            <dependent idx="22">that</dependent>
          </dep>
          <dep type="det">
            <governor idx="24">country</governor>
            <dependent idx="23">the</dependent>
          </dep>
          <dep type="poss">
            <governor idx="26">economy</governor>
            <dependent idx="24">country</dependent>
          </dep>
          <dep type="possessive">
            <governor idx="24">country</governor>
            <dependent idx="25">'s</dependent>
          </dep>
          <dep type="nsubj">
            <governor idx="29">growing</governor>
            <dependent idx="26">economy</dependent>
          </dep>
          <dep type="aux">
            <governor idx="29">growing</governor>
            <dependent idx="27">might</dependent>
          </dep>
          <dep type="aux">
            <governor idx="29">growing</governor>
            <dependent idx="28">be</dependent>
          </dep>
          <dep type="ccomp">
            <governor idx="21">emerged</governor>
            <dependent idx="29">growing</dependent>
          </dep>
          <dep type="prep">
            <governor idx="29">growing</governor>
            <dependent idx="30">at</dependent>
          </dep>
          <dep type="det">
            <governor idx="33">pace</governor>
            <dependent idx="31">an</dependent>
          </dep>
          <dep type="amod">
            <governor idx="33">pace</governor>
            <dependent idx="32">unsustainable</dependent>
          </dep>
          <dep type="pobj">
            <governor idx="30">at</governor>
            <dependent idx="33">pace</dependent>
          </dep>
          <dep type="mark">
            <governor idx="37">soar</governor>
            <dependent idx="34">as</dependent>
          </dep>
          <dep type="nn">
            <governor idx="36">prices</governor>
            <dependent idx="35">property</dependent>
          </dep>
          <dep type="nsubj">
            <governor idx="37">soar</governor>
            <dependent idx="36">prices</dependent>
          </dep>
          <dep type="advcl">
            <governor idx="29">growing</governor>
            <dependent idx="37">soar</dependent>
          </dep>
        </basic-dependencies>
        <collapsed-dependencies>
          <dep type="poss">
            <governor idx="4">bank</governor>
            <dependent idx="1">China</dependent>
          </dep>
          <dep type="amod">
            <governor idx="4">bank</governor>
            <dependent idx="3">central</dependent>
          </dep>
          <dep type="nsubj">
            <governor idx="5">said</governor>
            <dependent idx="4">bank</dependent>
          </dep>
          <dep type="amod">
            <governor idx="7">Wednesday</governor>
            <dependent idx="6">late</dependent>
          </dep>
          <dep type="tmod">
            <governor idx="5">said</governor>
            <dependent idx="7">Wednesday</dependent>
          </dep>
          <dep type="complm">
            <governor idx="11">raising</governor>
            <dependent idx="8">that</dependent>
          </dep>
          <dep type="nsubj">
            <governor idx="11">raising</governor>
            <dependent idx="9">it</dependent>
          </dep>
          <dep type="aux">
            <governor idx="11">raising</governor>
            <dependent idx="10">was</dependent>
          </dep>
          <dep type="ccomp">
            <governor idx="5">said</governor>
            <dependent idx="11">raising</dependent>
          </dep>
          <dep type="det">
            <governor idx="14">rate</governor>
            <dependent idx="12">the</dependent>
          </dep>
          <dep type="nn">
            <governor idx="14">rate</governor>
            <dependent idx="13">interest</dependent>
          </dep>
          <dep type="dobj">
            <governor idx="11">raising</governor>
            <dependent idx="14">rate</dependent>
          </dep>
          <dep type="prep_on">
            <governor idx="11">raising</governor>
            <dependent idx="16">mortgages</dependent>
          </dep>
          <dep type="mark">
            <governor idx="21">emerged</governor>
            <dependent idx="18">after</dependent>
          </dep>
          <dep type="amod">
            <governor idx="20">signs</governor>
            <dependent idx="19">more</dependent>
          </dep>
          <dep type="nsubj">
            <governor idx="21">emerged</governor>
            <dependent idx="20">signs</dependent>
          </dep>
          <dep type="advcl">
            <governor idx="11">raising</governor>
            <dependent idx="21">emerged</dependent>
          </dep>
          <dep type="complm">
            <governor idx="29">growing</governor>
            <dependent idx="22">that</dependent>
          </dep>
          <dep type="det">
            <governor idx="24">country</governor>
            <dependent idx="23">the</dependent>
          </dep>
          <dep type="poss">
            <governor idx="26">economy</governor>
            <dependent idx="24">country</dependent>
          </dep>
          <dep type="nsubj">
            <governor idx="29">growing</governor>
            <dependent idx="26">economy</dependent>
          </dep>
          <dep type="aux">
            <governor idx="29">growing</governor>
            <dependent idx="27">might</dependent>
          </dep>
          <dep type="aux">
            <governor idx="29">growing</governor>
            <dependent idx="28">be</dependent>
          </dep>
          <dep type="ccomp">
            <governor idx="21">emerged</governor>
            <dependent idx="29">growing</dependent>
          </dep>
          <dep type="det">
            <governor idx="33">pace</governor>
            <dependent idx="31">an</dependent>
          </dep>
          <dep type="amod">
            <governor idx="33">pace</governor>
            <dependent idx="32">unsustainable</dependent>
          </dep>
          <dep type="prep_at">
            <governor idx="29">growing</governor>
            <dependent idx="33">pace</dependent>
          </dep>
          <dep type="mark">
            <governor idx="37">soar</governor>
            <dependent idx="34">as</dependent>
          </dep>
          <dep type="nn">
            <governor idx="36">prices</governor>
            <dependent idx="35">property</dependent>
          </dep>
          <dep type="nsubj">
            <governor idx="37">soar</governor>
            <dependent idx="36">prices</dependent>
          </dep>
          <dep type="advcl">
            <governor idx="29">growing</governor>
            <dependent idx="37">soar</dependent>
          </dep>
        </collapsed-dependencies>
        <collapsed-ccprocessed-dependencies>
          <dep type="poss">
            <governor idx="4">bank</governor>
            <dependent idx="1">China</dependent>
          </dep>
          <dep type="amod">
            <governor idx="4">bank</governor>
            <dependent idx="3">central</dependent>
          </dep>
          <dep type="nsubj">
            <governor idx="5">said</governor>
            <dependent idx="4">bank</dependent>
          </dep>
          <dep type="amod">
            <governor idx="7">Wednesday</governor>
            <dependent idx="6">late</dependent>
          </dep>
          <dep type="tmod">
            <governor idx="5">said</governor>
            <dependent idx="7">Wednesday</dependent>
          </dep>
          <dep type="complm">
            <governor idx="11">raising</governor>
            <dependent idx="8">that</dependent>
          </dep>
          <dep type="nsubj">
            <governor idx="11">raising</governor>
            <dependent idx="9">it</dependent>
          </dep>
          <dep type="aux">
            <governor idx="11">raising</governor>
            <dependent idx="10">was</dependent>
          </dep>
          <dep type="ccomp">
            <governor idx="5">said</governor>
            <dependent idx="11">raising</dependent>
          </dep>
          <dep type="det">
            <governor idx="14">rate</governor>
            <dependent idx="12">the</dependent>
          </dep>
          <dep type="nn">
            <governor idx="14">rate</governor>
            <dependent idx="13">interest</dependent>
          </dep>
          <dep type="dobj">
            <governor idx="11">raising</governor>
            <dependent idx="14">rate</dependent>
          </dep>
          <dep type="prep_on">
            <governor idx="11">raising</governor>
            <dependent idx="16">mortgages</dependent>
          </dep>
          <dep type="mark">
            <governor idx="21">emerged</governor>
            <dependent idx="18">after</dependent>
          </dep>
          <dep type="amod">
            <governor idx="20">signs</governor>
            <dependent idx="19">more</dependent>
          </dep>
          <dep type="nsubj">
            <governor idx="21">emerged</governor>
            <dependent idx="20">signs</dependent>
          </dep>
          <dep type="advcl">
            <governor idx="11">raising</governor>
            <dependent idx="21">emerged</dependent>
          </dep>
          <dep type="complm">
            <governor idx="29">growing</governor>
            <dependent idx="22">that</dependent>
          </dep>
          <dep type="det">
            <governor idx="24">country</governor>
            <dependent idx="23">the</dependent>
          </dep>
          <dep type="poss">
            <governor idx="26">economy</governor>
            <dependent idx="24">country</dependent>
          </dep>
          <dep type="nsubj">
            <governor idx="29">growing</governor>
            <dependent idx="26">economy</dependent>
          </dep>
          <dep type="aux">
            <governor idx="29">growing</governor>
            <dependent idx="27">might</dependent>
          </dep>
          <dep type="aux">
            <governor idx="29">growing</governor>
            <dependent idx="28">be</dependent>
          </dep>
          <dep type="ccomp">
            <governor idx="21">emerged</governor>
            <dependent idx="29">growing</dependent>
          </dep>
          <dep type="det">
            <governor idx="33">pace</governor>
            <dependent idx="31">an</dependent>
          </dep>
          <dep type="amod">
            <governor idx="33">pace</governor>
            <dependent idx="32">unsustainable</dependent>
          </dep>
          <dep type="prep_at">
            <governor idx="29">growing</governor>
            <dependent idx="33">pace</dependent>
          </dep>
          <dep type="mark">
            <governor idx="37">soar</governor>
            <dependent idx="34">as</dependent>
          </dep>
          <dep type="nn">
            <governor idx="36">prices</governor>
            <dependent idx="35">property</dependent>
          </dep>
          <dep type="nsubj">
            <governor idx="37">soar</governor>
            <dependent idx="36">prices</dependent>
          </dep>
          <dep type="advcl">
            <governor idx="29">growing</governor>
            <dependent idx="37">soar</dependent>
          </dep>
        </collapsed-ccprocessed-dependencies>
      </sentence>
      <sentence id="2">
        <tokens>
          <token id="1">
            <word>The</word>
            <lemma>the</lemma>
            <CharacterOffsetBegin>212</CharacterOffsetBegin>
            <CharacterOffsetEnd>215</CharacterOffsetEnd>
            <POS>DT</POS>
            <NER>O</NER>
          </token>
          <token id="2">
            <word>minimum</word>
            <lemma>minimum</lemma>
            <CharacterOffsetBegin>216</CharacterOffsetBegin>
            <CharacterOffsetEnd>223</CharacterOffsetEnd>
            <POS>JJ</POS>
            <NER>O</NER>
          </token>
          <token id="3">
            <word>interest</word>
            <lemma>interest</lemma>
            <CharacterOffsetBegin>224</CharacterOffsetBegin>
            <CharacterOffsetEnd>232</CharacterOffsetEnd>
            <POS>NN</POS>
            <NER>O</NER>
          </token>
          <token id="4">
            <word>rate</word>
            <lemma>rate</lemma>
            <CharacterOffsetBegin>233</CharacterOffsetBegin>
            <CharacterOffsetEnd>237</CharacterOffsetEnd>
            <POS>NN</POS>
            <NER>O</NER>
          </token>
          <token id="5">
            <word>for</word>
            <lemma>for</lemma>
            <CharacterOffsetBegin>238</CharacterOffsetBegin>
            <CharacterOffsetEnd>241</CharacterOffsetEnd>
            <POS>IN</POS>
            <NER>O</NER>
          </token>
          <token id="6">
            <word>housing</word>
            <lemma>housing</lemma>
            <CharacterOffsetBegin>242</CharacterOffsetBegin>
            <CharacterOffsetEnd>249</CharacterOffsetEnd>
            <POS>NN</POS>
            <NER>O</NER>
          </token>
          <token id="7">
            <word>loans</word>
            <lemma>loan</lemma>
            <CharacterOffsetBegin>250</CharacterOffsetBegin>
            <CharacterOffsetEnd>255</CharacterOffsetEnd>
            <POS>NNS</POS>
            <NER>O</NER>
          </token>
          <token id="8">
            <word>of</word>
            <lemma>of</lemma>
            <CharacterOffsetBegin>256</CharacterOffsetBegin>
            <CharacterOffsetEnd>258</CharacterOffsetEnd>
            <POS>IN</POS>
            <NER>O</NER>
          </token>
          <token id="9">
            <word>five</word>
            <lemma>five</lemma>
            <CharacterOffsetBegin>259</CharacterOffsetBegin>
            <CharacterOffsetEnd>263</CharacterOffsetEnd>
            <POS>CD</POS>
            <NER>DURATION</NER>
            <Timex tid="t1" type="DURATION">P5Y</Timex>
          </token>
          <token id="10">
            <word>years</word>
            <lemma>year</lemma>
            <CharacterOffsetBegin>264</CharacterOffsetBegin>
            <CharacterOffsetEnd>269</CharacterOffsetEnd>
            <POS>NNS</POS>
            <NER>NUMBER</NER>
            <NormalizedNER>&gt;=0.0</NormalizedNER>
            <Timex tid="t1" type="DURATION">P5Y</Timex>
          </token>
          <token id="11">
            <word>or</word>
            <lemma>or</lemma>
            <CharacterOffsetBegin>270</CharacterOffsetBegin>
            <CharacterOffsetEnd>272</CharacterOffsetEnd>
            <POS>CC</POS>
            <NER>O</NER>
          </token>
          <token id="12">
            <word>more</word>
            <lemma>more</lemma>
            <CharacterOffsetBegin>273</CharacterOffsetBegin>
            <CharacterOffsetEnd>277</CharacterOffsetEnd>
            <POS>JJR</POS>
            <NER>O</NER>
          </token>
          <token id="13">
            <word>will</word>
            <lemma>will</lemma>
            <CharacterOffsetBegin>278</CharacterOffsetBegin>
            <CharacterOffsetEnd>282</CharacterOffsetEnd>
            <POS>MD</POS>
            <NER>O</NER>
          </token>
          <token id="14">
            <word>rise</word>
            <lemma>rise</lemma>
            <CharacterOffsetBegin>283</CharacterOffsetBegin>
            <CharacterOffsetEnd>287</CharacterOffsetEnd>
            <POS>VB</POS>
            <NER>O</NER>
          </token>
          <token id="15">
            <word>to</word>
            <lemma>to</lemma>
            <CharacterOffsetBegin>288</CharacterOffsetBegin>
            <CharacterOffsetEnd>290</CharacterOffsetEnd>
            <POS>TO</POS>
            <NER>O</NER>
          </token>
          <token id="16">
            <word>5.51</word>
            <lemma>5.51</lemma>
            <CharacterOffsetBegin>291</CharacterOffsetBegin>
            <CharacterOffsetEnd>295</CharacterOffsetEnd>
            <POS>CD</POS>
            <NER>PERCENT</NER>
            <NormalizedNER>%5.51</NormalizedNER>
          </token>
          <token id="17">
            <word>percent</word>
            <lemma>percent</lemma>
            <CharacterOffsetBegin>296</CharacterOffsetBegin>
            <CharacterOffsetEnd>303</CharacterOffsetEnd>
            <POS>NN</POS>
            <NER>PERCENT</NER>
            <NormalizedNER>%5.51</NormalizedNER>
          </token>
          <token id="18">
            <word>,</word>
            <lemma>,</lemma>
            <CharacterOffsetBegin>303</CharacterOffsetBegin>
            <CharacterOffsetEnd>304</CharacterOffsetEnd>
            <POS>,</POS>
            <NER>O</NER>
          </token>
          <token id="19">
            <word>from</word>
            <lemma>from</lemma>
            <CharacterOffsetBegin>305</CharacterOffsetBegin>
            <CharacterOffsetEnd>309</CharacterOffsetEnd>
            <POS>IN</POS>
            <NER>O</NER>
          </token>
          <token id="20">
            <word>5.31</word>
            <lemma>5.31</lemma>
            <CharacterOffsetBegin>310</CharacterOffsetBegin>
            <CharacterOffsetEnd>314</CharacterOffsetEnd>
            <POS>CD</POS>
            <NER>PERCENT</NER>
            <NormalizedNER>%5.31</NormalizedNER>
          </token>
          <token id="21">
            <word>percent</word>
            <lemma>percent</lemma>
            <CharacterOffsetBegin>315</CharacterOffsetBegin>
            <CharacterOffsetEnd>322</CharacterOffsetEnd>
            <POS>NN</POS>
            <NER>PERCENT</NER>
            <NormalizedNER>%5.31</NormalizedNER>
          </token>
          <token id="22">
            <word>.</word>
            <lemma>.</lemma>
            <CharacterOffsetBegin>322</CharacterOffsetBegin>
            <CharacterOffsetEnd>323</CharacterOffsetEnd>
            <POS>.</POS>
            <NER>O</NER>
          </token>
        </tokens>
        <parse>(ROOT (S (NP (NP (DT The) (JJ minimum) (NN interest) (NN rate)) (PP (IN for) (NP (NP (NN housing) (NNS loans)) (PP (IN of) (NP (CD five) (NNS years) (QP (CC or) (JJR more))))))) (VP (MD will) (VP (VB rise) (PP (TO to) (NP (CD 5.51) (NN percent))) (, ,) (PP (IN from) (NP (CD 5.31) (NN percent))))) (. .))) </parse>
        <basic-dependencies>
          <dep type="det">
            <governor idx="4">rate</governor>
            <dependent idx="1">The</dependent>
          </dep>
          <dep type="amod">
            <governor idx="4">rate</governor>
            <dependent idx="2">minimum</dependent>
          </dep>
          <dep type="nn">
            <governor idx="4">rate</governor>
            <dependent idx="3">interest</dependent>
          </dep>
          <dep type="nsubj">
            <governor idx="14">rise</governor>
            <dependent idx="4">rate</dependent>
          </dep>
          <dep type="prep">
            <governor idx="4">rate</governor>
            <dependent idx="5">for</dependent>
          </dep>
          <dep type="nn">
            <governor idx="7">loans</governor>
            <dependent idx="6">housing</dependent>
          </dep>
          <dep type="pobj">
            <governor idx="5">for</governor>
            <dependent idx="7">loans</dependent>
          </dep>
          <dep type="prep">
            <governor idx="7">loans</governor>
            <dependent idx="8">of</dependent>
          </dep>
          <dep type="num">
            <governor idx="10">years</governor>
            <dependent idx="9">five</dependent>
          </dep>
          <dep type="pobj">
            <governor idx="8">of</governor>
            <dependent idx="10">years</dependent>
          </dep>
          <dep type="cc">
            <governor idx="12">more</governor>
            <dependent idx="11">or</dependent>
          </dep>
          <dep type="num">
            <governor idx="10">years</governor>
            <dependent idx="12">more</dependent>
          </dep>
          <dep type="aux">
            <governor idx="14">rise</governor>
            <dependent idx="13">will</dependent>
          </dep>
          <dep type="prep">
            <governor idx="14">rise</governor>
            <dependent idx="15">to</dependent>
          </dep>
          <dep type="num">
            <governor idx="17">percent</governor>
            <dependent idx="16">5.51</dependent>
          </dep>
          <dep type="pobj">
            <governor idx="15">to</governor>
            <dependent idx="17">percent</dependent>
          </dep>
          <dep type="prep">
            <governor idx="14">rise</governor>
            <dependent idx="19">from</dependent>
          </dep>
          <dep type="num">
            <governor idx="21">percent</governor>
            <dependent idx="20">5.31</dependent>
          </dep>
          <dep type="pobj">
            <governor idx="19">from</governor>
            <dependent idx="21">percent</dependent>
          </dep>
        </basic-dependencies>
        <collapsed-dependencies>
          <dep type="det">
            <governor idx="4">rate</governor>
            <dependent idx="1">The</dependent>
          </dep>
          <dep type="amod">
            <governor idx="4">rate</governor>
            <dependent idx="2">minimum</dependent>
          </dep>
          <dep type="nn">
            <governor idx="4">rate</governor>
            <dependent idx="3">interest</dependent>
          </dep>
          <dep type="nsubj">
            <governor idx="14">rise</governor>
            <dependent idx="4">rate</dependent>
          </dep>
          <dep type="nn">
            <governor idx="7">loans</governor>
            <dependent idx="6">housing</dependent>
          </dep>
          <dep type="prep_for">
            <governor idx="4">rate</governor>
            <dependent idx="7">loans</dependent>
          </dep>
          <dep type="num">
            <governor idx="10">years</governor>
            <dependent idx="9">five</dependent>
          </dep>
          <dep type="prep_of">
            <governor idx="7">loans</governor>
            <dependent idx="10">years</dependent>
          </dep>
          <dep type="cc">
            <governor idx="12">more</governor>
            <dependent idx="11">or</dependent>
          </dep>
          <dep type="num">
            <governor idx="10">years</governor>
            <dependent idx="12">more</dependent>
          </dep>
          <dep type="aux">
            <governor idx="14">rise</governor>
            <dependent idx="13">will</dependent>
          </dep>
          <dep type="num">
            <governor idx="17">percent</governor>
            <dependent idx="16">5.51</dependent>
          </dep>
          <dep type="prep_to">
            <governor idx="14">rise</governor>
            <dependent idx="17">percent</dependent>
          </dep>
          <dep type="num">
            <governor idx="21">percent</governor>
            <dependent idx="20">5.31</dependent>
          </dep>
          <dep type="prep_from">
            <governor idx="14">rise</governor>
            <dependent idx="21">percent</dependent>
          </dep>
        </collapsed-dependencies>
        <collapsed-ccprocessed-dependencies>
          <dep type="det">
            <governor idx="4">rate</governor>
            <dependent idx="1">The</dependent>
          </dep>
          <dep type="amod">
            <governor idx="4">rate</governor>
            <dependent idx="2">minimum</dependent>
          </dep>
          <dep type="nn">
            <governor idx="4">rate</governor>
            <dependent idx="3">interest</dependent>
          </dep>
          <dep type="nsubj">
            <governor idx="14">rise</governor>
            <dependent idx="4">rate</dependent>
          </dep>
          <dep type="nn">
            <governor idx="7">loans</governor>
            <dependent idx="6">housing</dependent>
          </dep>
          <dep type="prep_for">
            <governor idx="4">rate</governor>
            <dependent idx="7">loans</dependent>
          </dep>
          <dep type="num">
            <governor idx="10">years</governor>
            <dependent idx="9">five</dependent>
          </dep>
          <dep type="prep_of">
            <governor idx="7">loans</governor>
            <dependent idx="10">years</dependent>
          </dep>
          <dep type="cc">
            <governor idx="12">more</governor>
            <dependent idx="11">or</dependent>
          </dep>
          <dep type="num">
            <governor idx="10">years</governor>
            <dependent idx="12">more</dependent>
          </dep>
          <dep type="aux">
            <governor idx="14">rise</governor>
            <dependent idx="13">will</dependent>
          </dep>
          <dep type="num">
            <governor idx="17">percent</governor>
            <dependent idx="16">5.51</dependent>
          </dep>
          <dep type="prep_to">
            <governor idx="14">rise</governor>
            <dependent idx="17">percent</dependent>
          </dep>
          <dep type="num">
            <governor idx="21">percent</governor>
            <dependent idx="20">5.31</dependent>
          </dep>
          <dep type="prep_from">
            <governor idx="14">rise</governor>
            <dependent idx="21">percent</dependent>
          </dep>
        </collapsed-ccprocessed-dependencies>
      </sentence>
      <sentence id="3">
        <tokens>
          <token id="1">
            <word>Banks</word>
            <lemma>bank</lemma>
            <CharacterOffsetBegin>324</CharacterOffsetBegin>
            <CharacterOffsetEnd>329</CharacterOffsetEnd>
            <POS>NNS</POS>
            <NER>O</NER>
          </token>
          <token id="2">
            <word>will</word>
            <lemma>will</lemma>
            <CharacterOffsetBegin>330</CharacterOffsetBegin>
            <CharacterOffsetEnd>334</CharacterOffsetEnd>
            <POS>MD</POS>
            <NER>O</NER>
          </token>
          <token id="3">
            <word>also</word>
            <lemma>also</lemma>
            <CharacterOffsetBegin>335</CharacterOffsetBegin>
            <CharacterOffsetEnd>339</CharacterOffsetEnd>
            <POS>RB</POS>
            <NER>O</NER>
          </token>
          <token id="4">
            <word>be</word>
            <lemma>be</lemma>
            <CharacterOffsetBegin>340</CharacterOffsetBegin>
            <CharacterOffsetEnd>342</CharacterOffsetEnd>
            <POS>VB</POS>
            <NER>O</NER>
          </token>
          <token id="5">
            <word>encouraged</word>
            <lemma>encourage</lemma>
            <CharacterOffsetBegin>343</CharacterOffsetBegin>
            <CharacterOffsetEnd>353</CharacterOffsetEnd>
            <POS>VBN</POS>
            <NER>O</NER>
          </token>
          <token id="6">
            <word>to</word>
            <lemma>to</lemma>
            <CharacterOffsetBegin>354</CharacterOffsetBegin>
            <CharacterOffsetEnd>356</CharacterOffsetEnd>
            <POS>TO</POS>
            <NER>O</NER>
          </token>
          <token id="7">
            <word>require</word>
            <lemma>require</lemma>
            <CharacterOffsetBegin>357</CharacterOffsetBegin>
            <CharacterOffsetEnd>364</CharacterOffsetEnd>
            <POS>VB</POS>
            <NER>O</NER>
          </token>
          <token id="8">
            <word>down</word>
            <lemma>down</lemma>
            <CharacterOffsetBegin>365</CharacterOffsetBegin>
            <CharacterOffsetEnd>369</CharacterOffsetEnd>
            <POS>RP</POS>
            <NER>O</NER>
          </token>
          <token id="9">
            <word>payments</word>
            <lemma>payment</lemma>
            <CharacterOffsetBegin>370</CharacterOffsetBegin>
            <CharacterOffsetEnd>378</CharacterOffsetEnd>
            <POS>NNS</POS>
            <NER>O</NER>
          </token>
          <token id="10">
            <word>equal</word>
            <lemma>equal</lemma>
            <CharacterOffsetBegin>379</CharacterOffsetBegin>
            <CharacterOffsetEnd>384</CharacterOffsetEnd>
            <POS>JJ</POS>
            <NER>O</NER>
          </token>
          <token id="11">
            <word>to</word>
            <lemma>to</lemma>
            <CharacterOffsetBegin>385</CharacterOffsetBegin>
            <CharacterOffsetEnd>387</CharacterOffsetEnd>
            <POS>TO</POS>
            <NER>O</NER>
          </token>
          <token id="12">
            <word>30</word>
            <lemma>30</lemma>
            <CharacterOffsetBegin>388</CharacterOffsetBegin>
            <CharacterOffsetEnd>390</CharacterOffsetEnd>
            <POS>CD</POS>
            <NER>PERCENT</NER>
            <NormalizedNER>%30.0</NormalizedNER>
          </token>
          <token id="13">
            <word>percent</word>
            <lemma>percent</lemma>
            <CharacterOffsetBegin>391</CharacterOffsetBegin>
            <CharacterOffsetEnd>398</CharacterOffsetEnd>
            <POS>NN</POS>
            <NER>PERCENT</NER>
            <NormalizedNER>%30.0</NormalizedNER>
          </token>
          <token id="14">
            <word>of</word>
            <lemma>of</lemma>
            <CharacterOffsetBegin>399</CharacterOffsetBegin>
            <CharacterOffsetEnd>401</CharacterOffsetEnd>
            <POS>IN</POS>
            <NER>O</NER>
          </token>
          <token id="15">
            <word>the</word>
            <lemma>the</lemma>
            <CharacterOffsetBegin>402</CharacterOffsetBegin>
            <CharacterOffsetEnd>405</CharacterOffsetEnd>
            <POS>DT</POS>
            <NER>O</NER>
          </token>
          <token id="16">
            <word>purchase</word>
            <lemma>purchase</lemma>
            <CharacterOffsetBegin>406</CharacterOffsetBegin>
            <CharacterOffsetEnd>414</CharacterOffsetEnd>
            <POS>NN</POS>
            <NER>O</NER>
          </token>
          <token id="17">
            <word>price</word>
            <lemma>price</lemma>
            <CharacterOffsetBegin>415</CharacterOffsetBegin>
            <CharacterOffsetEnd>420</CharacterOffsetEnd>
            <POS>NN</POS>
            <NER>O</NER>
          </token>
          <token id="18">
            <word>,</word>
            <lemma>,</lemma>
            <CharacterOffsetBegin>420</CharacterOffsetBegin>
            <CharacterOffsetEnd>421</CharacterOffsetEnd>
            <POS>,</POS>
            <NER>O</NER>
          </token>
          <token id="19">
            <word>instead</word>
            <lemma>instead</lemma>
            <CharacterOffsetBegin>422</CharacterOffsetBegin>
            <CharacterOffsetEnd>429</CharacterOffsetEnd>
            <POS>RB</POS>
            <NER>O</NER>
          </token>
          <token id="20">
            <word>of</word>
            <lemma>of</lemma>
            <CharacterOffsetBegin>430</CharacterOffsetBegin>
            <CharacterOffsetEnd>432</CharacterOffsetEnd>
            <POS>IN</POS>
            <NER>O</NER>
          </token>
          <token id="21">
            <word>20</word>
            <lemma>20</lemma>
            <CharacterOffsetBegin>433</CharacterOffsetBegin>
            <CharacterOffsetEnd>435</CharacterOffsetEnd>
            <POS>CD</POS>
            <NER>PERCENT</NER>
            <NormalizedNER>%20.0</NormalizedNER>
          </token>
          <token id="22">
            <word>percent</word>
            <lemma>percent</lemma>
            <CharacterOffsetBegin>436</CharacterOffsetBegin>
            <CharacterOffsetEnd>443</CharacterOffsetEnd>
            <POS>NN</POS>
            <NER>PERCENT</NER>
            <NormalizedNER>%20.0</NormalizedNER>
          </token>
          <token id="23">
            <word>,</word>
            <lemma>,</lemma>
            <CharacterOffsetBegin>443</CharacterOffsetBegin>
            <CharacterOffsetEnd>444</CharacterOffsetEnd>
            <POS>,</POS>
            <NER>O</NER>
          </token>
          <token id="24">
            <word>in</word>
            <lemma>in</lemma>
            <CharacterOffsetBegin>445</CharacterOffsetBegin>
            <CharacterOffsetEnd>447</CharacterOffsetEnd>
            <POS>IN</POS>
            <NER>O</NER>
          </token>
          <token id="25">
            <word>cities</word>
            <lemma>city</lemma>
            <CharacterOffsetBegin>448</CharacterOffsetBegin>
            <CharacterOffsetEnd>454</CharacterOffsetEnd>
            <POS>NNS</POS>
            <NER>O</NER>
          </token>
          <token id="26">
            <word>that</word>
            <lemma>that</lemma>
            <CharacterOffsetBegin>455</CharacterOffsetBegin>
            <CharacterOffsetEnd>459</CharacterOffsetEnd>
            <POS>WDT</POS>
            <NER>O</NER>
          </token>
          <token id="27">
            <word>have</word>
            <lemma>have</lemma>
            <CharacterOffsetBegin>460</CharacterOffsetBegin>
            <CharacterOffsetEnd>464</CharacterOffsetEnd>
            <POS>VBP</POS>
            <NER>O</NER>
          </token>
          <token id="28">
            <word>experienced</word>
            <lemma>experience</lemma>
            <CharacterOffsetBegin>465</CharacterOffsetBegin>
            <CharacterOffsetEnd>476</CharacterOffsetEnd>
            <POS>VBN</POS>
            <NER>O</NER>
          </token>
          <token id="29">
            <word>especially</word>
            <lemma>especially</lemma>
            <CharacterOffsetBegin>477</CharacterOffsetBegin>
            <CharacterOffsetEnd>487</CharacterOffsetEnd>
            <POS>RB</POS>
            <NER>O</NER>
          </token>
          <token id="30">
            <word>rapid</word>
            <lemma>rapid</lemma>
            <CharacterOffsetBegin>488</CharacterOffsetBegin>
            <CharacterOffsetEnd>493</CharacterOffsetEnd>
            <POS>JJ</POS>
            <NER>O</NER>
          </token>
          <token id="31">
            <word>appreciation</word>
            <lemma>appreciation</lemma>
            <CharacterOffsetBegin>494</CharacterOffsetBegin>
            <CharacterOffsetEnd>506</CharacterOffsetEnd>
            <POS>NN</POS>
            <NER>O</NER>
          </token>
          <token id="32">
            <word>lately</word>
            <lemma>lately</lemma>
            <CharacterOffsetBegin>507</CharacterOffsetBegin>
            <CharacterOffsetEnd>513</CharacterOffsetEnd>
            <POS>RB</POS>
            <NER>O</NER>
          </token>
          <token id="33">
            <word>,</word>
            <lemma>,</lemma>
            <CharacterOffsetBegin>513</CharacterOffsetBegin>
            <CharacterOffsetEnd>514</CharacterOffsetEnd>
            <POS>,</POS>
            <NER>O</NER>
          </token>
          <token id="34">
            <word>the</word>
            <lemma>the</lemma>
            <CharacterOffsetBegin>515</CharacterOffsetBegin>
            <CharacterOffsetEnd>518</CharacterOffsetEnd>
            <POS>DT</POS>
            <NER>O</NER>
          </token>
          <token id="35">
            <word>People</word>
            <lemma>people</lemma>
            <CharacterOffsetBegin>519</CharacterOffsetBegin>
            <CharacterOffsetEnd>525</CharacterOffsetEnd>
            <POS>NNS</POS>
            <NER>ORGANIZATION</NER>
          </token>
          <token id="36">
            <word>'s</word>
            <lemma>'s</lemma>
            <CharacterOffsetBegin>525</CharacterOffsetBegin>
            <CharacterOffsetEnd>527</CharacterOffsetEnd>
            <POS>POS</POS>
            <NER>ORGANIZATION</NER>
          </token>
          <token id="37">
            <word>Bank</word>
            <lemma>Bank</lemma>
            <CharacterOffsetBegin>528</CharacterOffsetBegin>
            <CharacterOffsetEnd>532</CharacterOffsetEnd>
            <POS>NNP</POS>
            <NER>ORGANIZATION</NER>
          </token>
          <token id="38">
            <word>of</word>
            <lemma>of</lemma>
            <CharacterOffsetBegin>533</CharacterOffsetBegin>
            <CharacterOffsetEnd>535</CharacterOffsetEnd>
            <POS>IN</POS>
            <NER>ORGANIZATION</NER>
          </token>
          <token id="39">
            <word>China</word>
            <lemma>China</lemma>
            <CharacterOffsetBegin>536</CharacterOffsetBegin>
            <CharacterOffsetEnd>541</CharacterOffsetEnd>
            <POS>NNP</POS>
            <NER>ORGANIZATION</NER>
          </token>
          <token id="40">
            <word>said</word>
            <lemma>say</lemma>
            <CharacterOffsetBegin>542</CharacterOffsetBegin>
            <CharacterOffsetEnd>546</CharacterOffsetEnd>
            <POS>VBD</POS>
            <NER>O</NER>
          </token>
          <token id="41">
            <word>in</word>
            <lemma>in</lemma>
            <CharacterOffsetBegin>547</CharacterOffsetBegin>
            <CharacterOffsetEnd>549</CharacterOffsetEnd>
            <POS>IN</POS>
            <NER>O</NER>
          </token>
          <token id="42">
            <word>a</word>
            <lemma>a</lemma>
            <CharacterOffsetBegin>550</CharacterOffsetBegin>
            <CharacterOffsetEnd>551</CharacterOffsetEnd>
            <POS>DT</POS>
            <NER>O</NER>
          </token>
          <token id="43">
            <word>statement</word>
            <lemma>statement</lemma>
            <CharacterOffsetBegin>552</CharacterOffsetBegin>
            <CharacterOffsetEnd>561</CharacterOffsetEnd>
            <POS>NN</POS>
            <NER>O</NER>
          </token>
          <token id="44">
            <word>on</word>
            <lemma>on</lemma>
            <CharacterOffsetBegin>562</CharacterOffsetBegin>
            <CharacterOffsetEnd>564</CharacterOffsetEnd>
            <POS>IN</POS>
            <NER>O</NER>
          </token>
          <token id="45">
            <word>its</word>
            <lemma>its</lemma>
            <CharacterOffsetBegin>565</CharacterOffsetBegin>
            <CharacterOffsetEnd>568</CharacterOffsetEnd>
            <POS>PRP$</POS>
            <NER>O</NER>
          </token>
          <token id="46">
            <word>Web</word>
            <lemma>web</lemma>
            <CharacterOffsetBegin>569</CharacterOffsetBegin>
            <CharacterOffsetEnd>572</CharacterOffsetEnd>
            <POS>NN</POS>
            <NER>O</NER>
          </token>
          <token id="47">
            <word>site</word>
            <lemma>site</lemma>
            <CharacterOffsetBegin>573</CharacterOffsetBegin>
            <CharacterOffsetEnd>577</CharacterOffsetEnd>
            <POS>NN</POS>
            <NER>O</NER>
          </token>
          <token id="48">
            <word>.</word>
            <lemma>.</lemma>
            <CharacterOffsetBegin>577</CharacterOffsetBegin>
            <CharacterOffsetEnd>578</CharacterOffsetEnd>
            <POS>.</POS>
            <NER>O</NER>
          </token>
        </tokens>
        <parse>(ROOT (S (S (NP (NNS Banks)) (VP (MD will) (ADVP (RB also)) (VP (VB be) (VP (VBN encouraged) (S (VP (TO to) (VP (VB require) (PRT (RP down)) (NP (NP (NNS payments)) (ADJP (JJ equal) (PP (TO to) (NP (NP (CD 30) (NN percent)) (PP (IN of) (NP (DT the) (NN purchase) (NN price)))))) (, ,) (PP (RB instead) (IN of) (NP (CD 20) (NN percent))) (, ,) (PP (IN in) (NP (NP (NNS cities)) (SBAR (WHNP (WDT that)) (S (VP (VBP have) (VP (VBN experienced) (NP (RB especially) (JJ rapid) (NN appreciation)) (ADVP (RB lately)))))))))))))))) (, ,) (NP (NP (NP (DT the) (NNS People) (POS 's)) (NNP Bank)) (PP (IN of) (NP (NNP China)))) (VP (VBD said) (PP (IN in) (NP (DT a) (NN statement))) (PP (IN on) (NP (PRP$ its) (NN Web) (NN site)))) (. .))) </parse>
        <basic-dependencies>
          <dep type="nsubjpass">
            <governor idx="5">encouraged</governor>
            <dependent idx="1">Banks</dependent>
          </dep>
          <dep type="aux">
            <governor idx="5">encouraged</governor>
            <dependent idx="2">will</dependent>
          </dep>
          <dep type="advmod">
            <governor idx="5">encouraged</governor>
            <dependent idx="3">also</dependent>
          </dep>
          <dep type="auxpass">
            <governor idx="5">encouraged</governor>
            <dependent idx="4">be</dependent>
          </dep>
          <dep type="ccomp">
            <governor idx="40">said</governor>
            <dependent idx="5">encouraged</dependent>
          </dep>
          <dep type="aux">
            <governor idx="7">require</governor>
            <dependent idx="6">to</dependent>
          </dep>
          <dep type="xcomp">
            <governor idx="5">encouraged</governor>
            <dependent idx="7">require</dependent>
          </dep>
          <dep type="prt">
            <governor idx="7">require</governor>
            <dependent idx="8">down</dependent>
          </dep>
          <dep type="dobj">
            <governor idx="7">require</governor>
            <dependent idx="9">payments</dependent>
          </dep>
          <dep type="amod">
            <governor idx="9">payments</governor>
            <dependent idx="10">equal</dependent>
          </dep>
          <dep type="prep">
            <governor idx="10">equal</governor>
            <dependent idx="11">to</dependent>
          </dep>
          <dep type="num">
            <governor idx="13">percent</governor>
            <dependent idx="12">30</dependent>
          </dep>
          <dep type="pobj">
            <governor idx="11">to</governor>
            <dependent idx="13">percent</dependent>
          </dep>
          <dep type="prep">
            <governor idx="13">percent</governor>
            <dependent idx="14">of</dependent>
          </dep>
          <dep type="det">
            <governor idx="17">price</governor>
            <dependent idx="15">the</dependent>
          </dep>
          <dep type="nn">
            <governor idx="17">price</governor>
            <dependent idx="16">purchase</dependent>
          </dep>
          <dep type="pobj">
            <governor idx="14">of</governor>
            <dependent idx="17">price</dependent>
          </dep>
          <dep type="advmod">
            <governor idx="20">of</governor>
            <dependent idx="19">instead</dependent>
          </dep>
          <dep type="prep">
            <governor idx="9">payments</governor>
            <dependent idx="20">of</dependent>
          </dep>
          <dep type="num">
            <governor idx="22">percent</governor>
            <dependent idx="21">20</dependent>
          </dep>
          <dep type="pobj">
            <governor idx="20">of</governor>
            <dependent idx="22">percent</dependent>
          </dep>
          <dep type="prep">
            <governor idx="9">payments</governor>
            <dependent idx="24">in</dependent>
          </dep>
          <dep type="pobj">
            <governor idx="24">in</governor>
            <dependent idx="25">cities</dependent>
          </dep>
          <dep type="nsubj">
            <governor idx="28">experienced</governor>
            <dependent idx="26">that</dependent>
          </dep>
          <dep type="aux">
            <governor idx="28">experienced</governor>
            <dependent idx="27">have</dependent>
          </dep>
          <dep type="rcmod">
            <governor idx="25">cities</governor>
            <dependent idx="28">experienced</dependent>
          </dep>
          <dep type="advmod">
            <governor idx="31">appreciation</governor>
            <dependent idx="29">especially</dependent>
          </dep>
          <dep type="amod">
            <governor idx="31">appreciation</governor>
            <dependent idx="30">rapid</dependent>
          </dep>
          <dep type="dobj">
            <governor idx="28">experienced</governor>
            <dependent idx="31">appreciation</dependent>
          </dep>
          <dep type="advmod">
            <governor idx="28">experienced</governor>
            <dependent idx="32">lately</dependent>
          </dep>
          <dep type="det">
            <governor idx="35">People</governor>
            <dependent idx="34">the</dependent>
          </dep>
          <dep type="poss">
            <governor idx="37">Bank</governor>
            <dependent idx="35">People</dependent>
          </dep>
          <dep type="possessive">
            <governor idx="35">People</governor>
            <dependent idx="36">'s</dependent>
          </dep>
          <dep type="nsubj">
            <governor idx="40">said</governor>
            <dependent idx="37">Bank</dependent>
          </dep>
          <dep type="prep">
            <governor idx="37">Bank</governor>
            <dependent idx="38">of</dependent>
          </dep>
          <dep type="pobj">
            <governor idx="38">of</governor>
            <dependent idx="39">China</dependent>
          </dep>
          <dep type="prep">
            <governor idx="40">said</governor>
            <dependent idx="41">in</dependent>
          </dep>
          <dep type="det">
            <governor idx="43">statement</governor>
            <dependent idx="42">a</dependent>
          </dep>
          <dep type="pobj">
            <governor idx="41">in</governor>
            <dependent idx="43">statement</dependent>
          </dep>
          <dep type="prep">
            <governor idx="40">said</governor>
            <dependent idx="44">on</dependent>
          </dep>
          <dep type="poss">
            <governor idx="47">site</governor>
            <dependent idx="45">its</dependent>
          </dep>
          <dep type="nn">
            <governor idx="47">site</governor>
            <dependent idx="46">Web</dependent>
          </dep>
          <dep type="pobj">
            <governor idx="44">on</governor>
            <dependent idx="47">site</dependent>
          </dep>
        </basic-dependencies>
        <collapsed-dependencies>
          <dep type="nsubjpass">
            <governor idx="5">encouraged</governor>
            <dependent idx="1">Banks</dependent>
          </dep>
          <dep type="aux">
            <governor idx="5">encouraged</governor>
            <dependent idx="2">will</dependent>
          </dep>
          <dep type="advmod">
            <governor idx="5">encouraged</governor>
            <dependent idx="3">also</dependent>
          </dep>
          <dep type="auxpass">
            <governor idx="5">encouraged</governor>
            <dependent idx="4">be</dependent>
          </dep>
          <dep type="ccomp">
            <governor idx="40">said</governor>
            <dependent idx="5">encouraged</dependent>
          </dep>
          <dep type="aux">
            <governor idx="7">require</governor>
            <dependent idx="6">to</dependent>
          </dep>
          <dep type="xcomp">
            <governor idx="5">encouraged</governor>
            <dependent idx="7">require</dependent>
          </dep>
          <dep type="prt">
            <governor idx="7">require</governor>
            <dependent idx="8">down</dependent>
          </dep>
          <dep type="dobj">
            <governor idx="7">require</governor>
            <dependent idx="9">payments</dependent>
          </dep>
          <dep type="amod">
            <governor idx="9">payments</governor>
            <dependent idx="10">equal</dependent>
          </dep>
          <dep type="num">
            <governor idx="13">percent</governor>
            <dependent idx="12">30</dependent>
          </dep>
          <dep type="prep_to">
            <governor idx="10">equal</governor>
            <dependent idx="13">percent</dependent>
          </dep>
          <dep type="det">
            <governor idx="17">price</governor>
            <dependent idx="15">the</dependent>
          </dep>
          <dep type="nn">
            <governor idx="17">price</governor>
            <dependent idx="16">purchase</dependent>
          </dep>
          <dep type="prep_of">
            <governor idx="13">percent</governor>
            <dependent idx="17">price</dependent>
          </dep>
          <dep type="num">
            <governor idx="22">percent</governor>
            <dependent idx="21">20</dependent>
          </dep>
          <dep type="prep_instead_of">
            <governor idx="9">payments</governor>
            <dependent idx="22">percent</dependent>
          </dep>
          <dep type="prep_in">
            <governor idx="9">payments</governor>
            <dependent idx="25">cities</dependent>
          </dep>
          <dep type="nsubj">
            <governor idx="28">experienced</governor>
            <dependent idx="26">that</dependent>
          </dep>
          <dep type="aux">
            <governor idx="28">experienced</governor>
            <dependent idx="27">have</dependent>
          </dep>
          <dep type="rcmod">
            <governor idx="25">cities</governor>
            <dependent idx="28">experienced</dependent>
          </dep>
          <dep type="advmod">
            <governor idx="31">appreciation</governor>
            <dependent idx="29">especially</dependent>
          </dep>
          <dep type="amod">
            <governor idx="31">appreciation</governor>
            <dependent idx="30">rapid</dependent>
          </dep>
          <dep type="dobj">
            <governor idx="28">experienced</governor>
            <dependent idx="31">appreciation</dependent>
          </dep>
          <dep type="advmod">
            <governor idx="28">experienced</governor>
            <dependent idx="32">lately</dependent>
          </dep>
          <dep type="det">
            <governor idx="35">People</governor>
            <dependent idx="34">the</dependent>
          </dep>
          <dep type="poss">
            <governor idx="37">Bank</governor>
            <dependent idx="35">People</dependent>
          </dep>
          <dep type="nsubj">
            <governor idx="40">said</governor>
            <dependent idx="37">Bank</dependent>
          </dep>
          <dep type="prep_of">
            <governor idx="37">Bank</governor>
            <dependent idx="39">China</dependent>
          </dep>
          <dep type="det">
            <governor idx="43">statement</governor>
            <dependent idx="42">a</dependent>
          </dep>
          <dep type="prep_in">
            <governor idx="40">said</governor>
            <dependent idx="43">statement</dependent>
          </dep>
          <dep type="poss">
            <governor idx="47">site</governor>
            <dependent idx="45">its</dependent>
          </dep>
          <dep type="nn">
            <governor idx="47">site</governor>
            <dependent idx="46">Web</dependent>
          </dep>
          <dep type="prep_on">
            <governor idx="40">said</governor>
            <dependent idx="47">site</dependent>
          </dep>
        </collapsed-dependencies>
        <collapsed-ccprocessed-dependencies>
          <dep type="nsubjpass">
            <governor idx="5">encouraged</governor>
            <dependent idx="1">Banks</dependent>
          </dep>
          <dep type="aux">
            <governor idx="5">encouraged</governor>
            <dependent idx="2">will</dependent>
          </dep>
          <dep type="advmod">
            <governor idx="5">encouraged</governor>
            <dependent idx="3">also</dependent>
          </dep>
          <dep type="auxpass">
            <governor idx="5">encouraged</governor>
            <dependent idx="4">be</dependent>
          </dep>
          <dep type="ccomp">
            <governor idx="40">said</governor>
            <dependent idx="5">encouraged</dependent>
          </dep>
          <dep type="aux">
            <governor idx="7">require</governor>
            <dependent idx="6">to</dependent>
          </dep>
          <dep type="xcomp">
            <governor idx="5">encouraged</governor>
            <dependent idx="7">require</dependent>
          </dep>
          <dep type="prt">
            <governor idx="7">require</governor>
            <dependent idx="8">down</dependent>
          </dep>
          <dep type="dobj">
            <governor idx="7">require</governor>
            <dependent idx="9">payments</dependent>
          </dep>
          <dep type="amod">
            <governor idx="9">payments</governor>
            <dependent idx="10">equal</dependent>
          </dep>
          <dep type="num">
            <governor idx="13">percent</governor>
            <dependent idx="12">30</dependent>
          </dep>
          <dep type="prep_to">
            <governor idx="10">equal</governor>
            <dependent idx="13">percent</dependent>
          </dep>
          <dep type="det">
            <governor idx="17">price</governor>
            <dependent idx="15">the</dependent>
          </dep>
          <dep type="nn">
            <governor idx="17">price</governor>
            <dependent idx="16">purchase</dependent>
          </dep>
          <dep type="prep_of">
            <governor idx="13">percent</governor>
            <dependent idx="17">price</dependent>
          </dep>
          <dep type="num">
            <governor idx="22">percent</governor>
            <dependent idx="21">20</dependent>
          </dep>
          <dep type="prep_instead_of">
            <governor idx="9">payments</governor>
            <dependent idx="22">percent</dependent>
          </dep>
          <dep type="prep_in">
            <governor idx="9">payments</governor>
            <dependent idx="25">cities</dependent>
          </dep>
          <dep type="nsubj">
            <governor idx="28">experienced</governor>
            <dependent idx="26">that</dependent>
          </dep>
          <dep type="aux">
            <governor idx="28">experienced</governor>
            <dependent idx="27">have</dependent>
          </dep>
          <dep type="rcmod">
            <governor idx="25">cities</governor>
            <dependent idx="28">experienced</dependent>
          </dep>
          <dep type="advmod">
            <governor idx="31">appreciation</governor>
            <dependent idx="29">especially</dependent>
          </dep>
          <dep type="amod">
            <governor idx="31">appreciation</governor>
            <dependent idx="30">rapid</dependent>
          </dep>
          <dep type="dobj">
            <governor idx="28">experienced</governor>
            <dependent idx="31">appreciation</dependent>
          </dep>
          <dep type="advmod">
            <governor idx="28">experienced</governor>
            <dependent idx="32">lately</dependent>
          </dep>
          <dep type="det">
            <governor idx="35">People</governor>
            <dependent idx="34">the</dependent>
          </dep>
          <dep type="poss">
            <governor idx="37">Bank</governor>
            <dependent idx="35">People</dependent>
          </dep>
          <dep type="nsubj">
            <governor idx="40">said</governor>
            <dependent idx="37">Bank</dependent>
          </dep>
          <dep type="prep_of">
            <governor idx="37">Bank</governor>
            <dependent idx="39">China</dependent>
          </dep>
          <dep type="det">
            <governor idx="43">statement</governor>
            <dependent idx="42">a</dependent>
          </dep>
          <dep type="prep_in">
            <governor idx="40">said</governor>
            <dependent idx="43">statement</dependent>
          </dep>
          <dep type="poss">
            <governor idx="47">site</governor>
            <dependent idx="45">its</dependent>
          </dep>
          <dep type="nn">
            <governor idx="47">site</governor>
            <dependent idx="46">Web</dependent>
          </dep>
          <dep type="prep_on">
            <governor idx="40">said</governor>
            <dependent idx="47">site</dependent>
          </dep>
        </collapsed-ccprocessed-dependencies>
      </sentence>
    </sentences>
  </document>
</root>
